MANIFEST.in
README.txt
heddex.cityportal-configure.zcml
setup.cfg
setup.py
docs/HISTORY.txt
docs/INSTALL.txt
docs/LICENSE.GPL
docs/LICENSE.txt
heddex/__init__.py
heddex.cityportal.egg-info/PKG-INFO
heddex.cityportal.egg-info/SOURCES.txt
heddex.cityportal.egg-info/dependency_links.txt
heddex.cityportal.egg-info/entry_points.txt
heddex.cityportal.egg-info/namespace_packages.txt
heddex.cityportal.egg-info/not-zip-safe
heddex.cityportal.egg-info/paster_plugins.txt
heddex.cityportal.egg-info/requires.txt
heddex.cityportal.egg-info/top_level.txt
heddex/cityportal/__init__.py
heddex/cityportal/configure.zcml
heddex/cityportal/profiles.zcml
heddex/cityportal/setuphandlers.py
heddex/cityportal/skins.zcml
heddex/cityportal/tests.py
heddex/cityportal/version.txt
heddex/cityportal/browser/__init__.py
heddex/cityportal/browser/configure.zcml
heddex/cityportal/browser/interfaces.py
heddex/cityportal/browser/searchbox.pt
heddex/cityportal/browser/sections-footer.pt
heddex/cityportal/browser/sections.pt
heddex/cityportal/browser/viewlets.py
heddex/cityportal/portlets/__init__.py
heddex/cityportal/portlets/configure.zcml
heddex/cityportal/portlets/news.pt
heddex/cityportal/portlets/personaltools.pt
heddex/cityportal/portlets/personaltools.py
heddex/cityportal/profiles/default/cssregistry.xml
heddex/cityportal/profiles/default/heddex.cityportal_various.txt
heddex/cityportal/profiles/default/import_steps.xml
heddex/cityportal/profiles/default/metadata.xml
heddex/cityportal/profiles/default/portlets.xml
heddex/cityportal/profiles/default/skins.xml
heddex/cityportal/profiles/default/viewlets.xml
heddex/cityportal/skins/heddex_cityportal_images/bullet-large.gif
heddex/cityportal/skins/heddex_cityportal_images/bullet-large.gif.metadata
heddex/cityportal/skins/heddex_cityportal_images/bullet.gif
heddex/cityportal/skins/heddex_cityportal_images/bullet.gif.metadata
heddex/cityportal/skins/heddex_cityportal_images/dots-horizontal.gif
heddex/cityportal/skins/heddex_cityportal_images/dots-horizontal.gif.metadata
heddex/cityportal/skins/heddex_cityportal_images/dots-vertical.gif
heddex/cityportal/skins/heddex_cityportal_images/dots-vertical.gif.metadata
heddex/cityportal/skins/heddex_cityportal_images/globalnav-round-corners.png
heddex/cityportal/skins/heddex_cityportal_images/globalnav-round-corners.png.metadata
