Metadata-Version: 1.0
Name: heddex.cityportal
Version: 2.0
Summary: Installable theme for Plone
Home-page: http://www.heddex.biz
Author: Michael Krishtopa
Author-email: theo@heddex.biz
License: GPL
Keywords: web zope plone theme skin heddex theo michael krishtopa
Platform: UNKNOWN
Classifier: Framework :: Plone
Classifier: Framework :: Plone :: 4.1
Classifier: Programming Language :: Python
Classifier: Topic :: Software Development :: Libraries :: Python Modules
